{
  "fill" : {
    "solid" : "srgb:0.85882,0.20392,0.94902,1.00000"
  },
  "groups" : [
    {
      "layers" : [
        {
          "glass" : true,
          "hidden" : false,
          "image-name" : "eyes.svg",
          "name" : "eyes"
        }
      ],
      "shadow" : {
        "kind" : "neutral",
        "opacity" : 0.5
      },
      "translucency" : {
        "enabled" : true,
        "value" : 0.5
      }
    }
  ],
  "supported-platforms" : {
    "squares" : [
      "macOS"
    ]
  }
}